midterm/e8/f.v
module f(
    input logic[11:0] x,
    input logic[11:0] y,
    output logic[11:0] a,
    output logic[11:0] b
);
    assign a = x-2;
    assign b = y-2;
endmodule

midterm/e8/e8_waveforms.v
module e8_waveforms();
    logic[11:0] a,b,x,y;
    assign x = y+1;
    initial begin
        $dumpfile("e8_waveforms.vcd");
        $dumpvars(0,e8_waveforms);
        y = 0;
        repeat(4096)begin
            #1;
            $display("x=%d,y=%d",x,y);
            #1;
            y = y+1;
        end
    end
    f f1(
        .x(x),
        .y(y),
        .a(a),
        .b(b)
    );
endmodule

midterm/e8/e8_waveforms.vcd
$date
	Fri Nov 12 14:21:08 2021
$end
$version
	Icarus Verilog
$end
$timescale
	1s
$end
$scope module e8_waveforms $end
$var wire 12 ! x [11:0] $end
$var wire 12 " b [11:0] $end
$var wire 12 # a [11:0] $end
$var reg 12 $ y [11:0] $end
$scope module f1 $end
$var wire 12 % x [11:0] $end
$var wire 12 & y [11:0] $end
$var wire 12 ' b [11:0] $end
$var wire 12 ( a [11:0] $end
$upscope $end
$upscope $end
$enddefinitions $end
#0
$dumpvars
b111111111111 (
b111111111110 '
b0 &
b1 %
b0 $
b111111111111 #
b111111111110 "
b1 !
$end
#2
b0 #
b0 (
b10 !
b10 %
b111111111111 "
b111111111111 '
b1 $
b1 &
#4
b1 #
b1 (
b11 !
b11 %
b0 "
b0 '
b10 $
b10 &
#6
b10 #
b10 (
b100 !
b100 %
b1 "
b1 '
b11 $
b11 &
#8
b11 #
b11 (
b101 !
b101 %
b10 "
b10 '
b100 $
b100 &
#10
b100 #
b100 (
b110 !
b110 %
b11 "
b11 '
b101 $
b101 &
#12
b101 #
b101 (
b111 !
b111 %
b100 "
b100 '
b110 $
b110 &
#14
b110 #
b110 (
b1000 !
b1000 %
b101 "
b101 '
b111 $
b111 &
#16
b111 #
b111 (
b1001 !
b1001 %
b110 "
b110 '
b1000 $
b1000 &
#18
b1000 #
b1000 (
b1010 !
b1010 %
b111 "
b111 '
b1001 $
b1001 &
#20
b1001 #
b1001 (
b1011 !
b1011 %
b1000 "
b1000 '
b1010 $
b1010 &
#22
b1010 #
b1010 (
b1100 !
b1100 %
b1001 "
b1001 '
b1011 $
b1011 &
#24
b1011 #
b1011 (
b1101 !
b1101 %
b1010 "
b1010 '
b1100 $
b1100 &
#26
b1100 #
b1100 (
b1110 !
b1110 %
b1011 "
b1011 '
b1101 $
b1101 &
#28
b1101 #
b1101 (
b1111 !
b1111 %
b1100 "
b1100 '
b1110 $
b1110 &
#30
b1110 #
b1110 (
b10000 !
b10000 %
b1101 "
b1101 '
b1111 $
b1111 &
#32
b1111 #
b1111 (
b10001 !
b10001 %
b1110 "
b1110 '
b10000 $
b10000 &
#34
b10000 #
b10000 (
b10010 !
b10010 %
b1111 "
b1111 '
b10001 $
b10001 &
#36
b10001 #
b10001 (
b10011 !
b10011 %
b10000 "
b10000 '
b10010 $
b10010 &
#38
b10010 #
b10010 (
b10100 !
b10100 %
b10001 "
b10001 '
b10011 $
b10011 &
#40
b10011 #
b10011 (
b10101 !
b10101 %
b10010 "
b10010 '
b10100 $
b10100 &
#42
b10100 #
b10100 (
b10110 !
b10110 %
b10011 "
b10011 '
b10101 $
b10101 &
#44
b10101 #
b10101 (
b10111 !
b10111 %
b10100 "
b10100 '
b10110 $
b10110 &
#46
b10110 #
b10110 (
b11000 !
b11000 %
b10101 "
b10101 '
b10111 $
b10111 &
#48
b10111 #
b10111 (
b11001 !
b11001 %
b10110 "
b10110 '
b11000 $
b11000 &
#50
b11000 #
b11000 (
b11010 !
b11010 %
b10111 "
b10111 '
b11001 $
b11001 &
#52
b11001 #
b11001 (
b11011 !
b11011 %
b11000 "
b11000 '
b11010 $
b11010 &
#54
b11010 #
b11010 (
b11100 !
b11100 %
b11001 "
b11001 '
b11011 $
b11011 &
#56
b11011 #
b11011 (
b11101 !
b11101 %
b11010 "
b11010 '
b11100 $
b11100 &
#58
b11100 #
b11100 (
b11110 !
b11110 %
b11011 "
b11011 '
b11101 $
b11101 &
#60
b11101 #
b11101 (
b11111 !
b11111 %
b11100 "
b11100 '
b11110 $
b11110 &
#62
b11110 #
b11110 (
b100000 !
b100000 %
b11101 "
b11101 '
b11111 $
b11111 &
#64
b11111 #
b11111 (
b100001 !
b100001 %
b11110 "
b11110 '
b100000 $
b100000 &
#66
b100000 #
b100000 (
b100010 !
b100010 %
b11111 "
b11111 '
b100001 $
b100001 &
#68
b100001 #
b100001 (
b100011 !
b100011 %
b100000 "
b100000 '
b100010 $
b100010 &
#70
b100010 #
b100010 (
b100100 !
b100100 %
b100001 "
b100001 '
b100011 $
b100011 &
#72
b100011 #
b100011 (
b100101 !
b100101 %
b100010 "
b100010 '
b100100 $
b100100 &
#74
b100100 #
b100100 (
b100110 !
b100110 %
b100011 "
b100011 '
b100101 $
b100101 &
#76
b100101 #
b100101 (
b100111 !
b100111 %
b100100 "
b100100 '
b100110 $
b100110 &
#78
b100110 #
b100110 (
b101000 !
b101000 %
b100101 "
b100101 '
b100111 $
b100111 &
#80
b100111 #
b100111 (
b101001 !
b101001 %
b100110 "
b100110 '
b101000 $
b101000 &
#82
b101000 #
b101000 (
b101010 !
b101010 %
b100111 "
b100111 '
b101001 $
b101001 &
#84
b101001 #
b101001 (
b101011 !
b101011 %
b101000 "
b101000 '
b101010 $
b101010 &
#86
b101010 #
b101010 (
b101100 !
b101100 %
b101001 "
b101001 '
b101011 $
b101011 &
#88
b101011 #
b101011 (
b101101 !
b101101 %
b101010 "
b101010 '
b101100 $
b101100 &
#90
b101100 #
b101100 (
b101110 !
b101110 %
b101011 "
b101011 '
b101101 $
b101101 &
#92
b101101 #
b101101 (
b101111 !
b101111 %
b101100 "
b101100 '
b101110 $
b101110 &
#94
b101110 #
b101110 (
b110000 !
b110000 %
b101101 "
b101101 '
b101111 $
b101111 &
#96
b101111 #
b101111 (
b110001 !
b110001 %
b101110 "
b101110 '
b110000 $
b110000 &
#98
b110000 #
b110000 (
b110010 !
b110010 %
b101111 "
b101111 '
b110001 $
b110001 &
#100
b110001 #
b110001 (
b110011 !
b110011 %
b110000 "
b110000 '
b110010 $
b110010 &
#102
b110010 #
b110010 (
b110100 !
b110100 %
b110001 "
b110001 '
b110011 $
b110011 &
#104
b110011 #
b110011 (
b110101 !
b110101 %
b110010 "
b110010 '
b110100 $
b110100 &
#106
b110100 #
b110100 (
b110110 !
b110110 %
b110011 "
b110011 '
b110101 $
b110101 &
#108
b110101 #
b110101 (
b110111 !
b110111 %
b110100 "
b110100 '
b110110 $
b110110 &
#110
b110110 #
b110110 (
b111000 !
b111000 %
b110101 "
b110101 '
b110111 $
b110111 &
#112
b110111 #
b110111 (
b111001 !
b111001 %
b110110 "
b110110 '
b111000 $
b111000 &
#114
b111000 #
b111000 (
b111010 !
b111010 %
b110111 "
b110111 '
b111001 $
b111001 &
#116
b111001 #
b111001 (
b111011 !
b111011 %
b111000 "
b111000 '
b111010 $
b111010 &
#118
b111010 #
b111010 (
b111100 !
b111100 %
b111001 "
b111001 '
b111011 $
b111011 &
#120
b111011 #
b111011 (
b111101 !
b111101 %
b111010 "
b111010 '
b111100 $
b111100 &
#122
b111100 #
b111100 (
b111110 !
b111110 %
b111011 "
b111011 '
b111101 $
b111101 &
#124
b111101 #
b111101 (
b111111 !
b111111 %
b111100 "
b111100 '
b111110 $
b111110 &
#126
b111110 #
b111110 (
b1000000 !
b1000000 %
b111101 "
b111101 '
b111111 $
b111111 &
#128
b111111 #
b111111 (
b1000001 !
b1000001 %
b111110 "
b111110 '
b1000000 $
b1000000 &
#130
b1000000 #
b1000000 (
b1000010 !
b1000010 %
b111111 "
b111111 '
b1000001 $
b1000001 &
#132
b1000001 #
b1000001 (
b1000011 !
b1000011 %
b1000000 "
b1000000 '
b1000010 $
b1000010 &
#134
b1000010 #
b1000010 (
b1000100 !
b1000100 %
b1000001 "
b1000001 '
b1000011 $
b1000011 &
#136
b1000011 #
b1000011 (
b1000101 !
b1000101 %
b1000010 "
b1000010 '
b1000100 $
b1000100 &
#138
b1000100 #
b1000100 (
b1000110 !
b1000110 %
b1000011 "
b1000011 '
b1000101 $
b1000101 &
#140
b1000101 #
b1000101 (
b1000111 !
b1000111 %
b1000100 "
b1000100 '
b1000110 $
b1000110 &
#142
b1000110 #
b1000110 (
b1001000 !
b1001000 %
b1000101 "
b1000101 '
b1000111 $
b1000111 &
#144
b1000111 #
b1000111 (
b1001001 !
b1001001 %
b1000110 "
b1000110 '
b1001000 $
b1001000 &
#146
b1001000 #
b1001000 (
b1001010 !
b1001010 %
b1000111 "
b1000111 '
b1001001 $
b1001001 &
#148
b1001001 #
b1001001 (
b1001011 !
b1001011 %
b1001000 "
b1001000 '
b1001010 $
b1001010 &
#150
b1001010 #
b1001010 (
b1001100 !
b1001100 %
b1001001 "
b1001001 '
b1001011 $
b1001011 &
#152
b1001011 #
b1001011 (
b1001101 !
b1001101 %
b1001010 "
b1001010 '
b1001100 $
b1001100 &
#154
b1001100 #
b1001100 (
b1001110 !
b1001110 %
b1001011 "
b1001011 '
b1001101 $
b1001101 &
#156
b1001101 #
b1001101 (
b1001111 !
b1001111 %
b1001100 "
b1001100 '
b1001110 $
b1001110 &
#158
b1001110 #
b1001110 (
b1010000 !
b1010000 %
b1001101 "
b1001101 '
b1001111 $
b1001111 &
#160
b1001111 #
b1001111 (
b1010001 !
b1010001 %
b1001110 "
b1001110 '
b1010000 $
b1010000 &
#162
b1010000 #
b1010000 (
b1010010 !
b1010010 %
b1001111 "
b1001111 '
b1010001 $
b1010001 &
#164
b1010001 #
b1010001 (
b1010011 !
b1010011 %
b1010000 "
b1010000 '
b1010010 $
b1010010 &
#166
b1010010 #
b1010010 (
b1010100 !
b1010100 %
b1010001 "
b1010001 '
b1010011 $
b1010011 &
#168
b1010011 #
b1010011 (
b1010101 !
b1010101 %
b1010010 "
b1010010 '
b1010100 $
b1010100 &
#170
b1010100 #
b1010100 (
b1010110 !
b1010110 %
b1010011 "
b1010011 '
b1010101 $
b1010101 &
#172
b1010101 #
b1010101 (
b1010111 !
b1010111 %
b1010100 "
b1010100 '
b1010110 $
b1010110 &
#174
b1010110 #
b1010110 (
b1011000 !
b1011000 %
b1010101 "
b1010101 '
b1010111 $
b1010111 &
#176
b1010111 #
b1010111 (
b1011001 !
b1011001 %
b1010110 "
b1010110 '
b1011000 $
b1011000 &
#178
b1011000 #
b1011000 (
b1011010 !
b1011010 %
b1010111 "
b1010111 '
b1011001 $
b1011001 &
#180
b1011001 #
b1011001 (
b1011011 !
b1011011 %
b1011000 "
b1011000 '
b1011010 $
b1011010 &
#182
b1011010 #
b1011010 (
b1011100 !
b1011100 %
b1011001 "
b1011001 '
b1011011 $
b1011011 &
#184
b1011011 #
b1011011 (
b1011101 !
b1011101 %
b1011010 "
b1011010 '
b1011100 $
b1011100 &
#186
b1011100 #
b1011100 (
b1011110 !
b1011110 %
b1011011 "
b1011011 '
b1011101 $
b1011101 &
#188
b1011101 #
b1011101 (
b1011111 !
b1011111 %
b1011100 "
b1011100 '
b1011110 $
b1011110 &
#190
b1011110 #
b1011110 (
b1100000 !
b1100000 %
b1011101 "
b1011101 '
b1011111 $
b1011111 &
#192
b1011111 #
b1011111 (
b1100001 !
b1100001 %
b1011110 "
b1011110 '
b1100000 $
b1100000 &
#194
b1100000 #
b1100000 (
b1100010 !
b1100010 %
b1011111 "
b1011111 '
b1100001 $
b1100001 &
#196
b1100001 #
b1100001 (
b1100011 !
b1100011 %
b1100000 "
b1100000 '
b1100010 $
b1100010 &
#198
b1100010 #
b1100010 (
b1100100 !
b1100100 %
b1100001 "
b1100001 '
b1100011 $
b1100011 &
#200
b1100011 #
b1100011 (
b1100101 !
b1100101 %
b1100010 "
b1100010 '
b1100100 $
b1100100 &
#202
b1100100 #
b1100100 (
b1100110 !
b1100110 %
b1100011 "
b1100011 '
b1100101 $
b1100101 &
#204
b1100101 #
b1100101 (
b1100111 !
b1100111 %
b1100100 "
b1100100 '
b1100110 $
b1100110 &
#206
b1100110 #
b1100110 (
b1101000 !
b1101000 %
b1100101 "
b1100101 '
b1100111 $
b1100111 &
#208
b1100111 #
b1100111 (
b1101001 !
b1101001 %
b1100110 "
b1100110 '
b1101000 $
b1101000 &
#210
b1101000 #
b1101000 (
b1101010 !
b1101010 %
b1100111 "
b1100111 '
b1101001 $
b1101001 &
#212
b1101001 #
b1101001 (
b1101011 !
b1101011 %
b1101000 "
b1101000 '
b1101010 $
b1101010 &
#214
b1101010 #
b1101010 (
b1101100 !
b1101100 %
b1101001 "
b1101001 '
b1101011 $
b1101011 &
#216
b1101011 #
b1101011 (
b1101101 !
b1101101 %
b1101010 "
b1101010 '
b1101100 $
b1101100 &
#218
b1101100 #
b1101100 (
b1101110 !
b1101110 %
b1101011 "
b1101011 '
b1101101 $
b1101101 &
#220
b1101101 #
b1101101 (
b1101111 !
b1101111 %
b1101100 "
b1101100 '
b1101110 $
b1101110 &
#222
b1101110 #
b1101110 (
b1110000 !
b1110000 %
b1101101 "
b1101101 '
b1101111 $
b1101111 &
#224
b1101111 #
b1101111 (
b1110001 !
b1110001 %
b1101110 "
b1101110 '
b1110000 $
b1110000 &
#226
b1110000 #
b1110000 (
b1110010 !
b1110010 %
b1101111 "
b1101111 '
b1110001 $
b1110001 &
#228
b1110001 #
b1110001 (
b1110011 !
b1110011 %
b1110000 "
b1110000 '
b1110010 $
b1110010 &
#230
b1110010 #
b1110010 (
b1110100 !
b1110100 %
b1110001 "
b1110001 '
b1110011 $
b1110011 &
#232
b1110011 #
b1110011 (
b1110101 !
b1110101 %
b1110010 "
b1110010 '
b1110100 $
b1110100 &
#234
b1110100 #
b1110100 (
b1110110 !
b1110110 %
b1110011 "
b1110011 '
b1110101 $
b1110101 &
#236
b1110101 #
b1110101 (
b1110111 !
b1110111 %
b1110100 "
b1110100 '
b1110110 $
b1110110 &
#238
b1110110 #
b1110110 (
b1111000 !
b1111000 %
b1110101 "
b1110101 '
b1110111 $
b1110111 &
#240
b1110111 #
b1110111 (
b1111001 !
b1111001 %
b1110110 "
b1110110 '
b1111000 $
b1111000 &
#242
b1111000 #
b1111000 (
b1111010 !
b1111010 %
b1110111 "
b1110111 '
b1111001 $
b1111001 &
#244
b1111001 #
b1111001 (
b1111011 !
b1111011 %
b1111000 "
b1111000 '
b1111010 $
b1111010 &
#246
b1111010 #
b1111010 (
b1111100 !
b1111100 %
b1111001 "
b1111001 '
b1111011 $
b1111011 &
#248
b1111011 #
b1111011 (
b1111101 !
b1111101 %
b1111010 "
b1111010 '
b1111100 $
b1111100 &
#250
b1111100 #
b1111100 (
b1111110 !
b1111110 %
b1111011 "
b1111011 '
b1111101 $
b1111101 &
#252
b1111101 #
b1111101 (
b1111111 !
b1111111 %
b1111100 "
b1111100 '
b1111110 $
b1111110 &
#254
b1111110 #
b1111110 (
b10000000 !
b10000000 %
b1111101 "
b1111101 '
b1111111 $
b1111111 &
#256
b1111111 #
b1111111 (
b10000001 !
b10000001 %
b1111110 "
b1111110 '
b10000000 $
b10000000 &
#258
b10000000 #
b10000000 (
b10000010 !
b10000010 %
b1111111 "
b1111111 '
b10000001 $
b10000001 &
#260
b10000001 #
b10000001 (
b10000011 !
b10000011 %
b10000000 "
b10000000 '
b10000010 $
b10000010 &
#262
b10000010 #
b10000010 (
b10000100 !
b10000100 %
b10000001 "
b10000001 '
b10000011 $
b10000011 &
#264
b10000011 #
b10000011 (
b10000101 !
b10000101 %
b10000010 "
b10000010 '
b10000100 $
b10000100 &
#266
b10000100 #
b10000100 (
b10000110 !
b10000110 %
b10000011 "
b10000011 '
b10000101 $
b10000101 &
#268
b10000101 #
b10000101 (
b10000111 !
b10000111 %
b10000100 "
b10000100 '
b10000110 $
b10000110 &
#270
b10000110 #
b10000110 (
b10001000 !
b10001000 %
b10000101 "
b10000101 '
b10000111 $
b10000111 &
#272
b10000111 #
b10000111 (
b10001001 !
b10001001 %
b10000110 "
b10000110 '
b10001000 $
b10001000 &
#274
b10001000 #
b10001000 (
b10001010 !
b10001010 %
b10000111 "
b10000111 '
b10001001 $
b10001001 &
#276
b10001001 #
b10001001 (
b10001011 !
b10001011 %
b10001000 "
b10001000 '
b10001010 $
b10001010 &
#278
b10001010 #
b10001010 (
b10001100 !
b10001100 %
b10001001 "
b10001001 '
b10001011 $
b10001011 &
#280
b10001011 #
b10001011 (
b10001101 !
b10001101 %
b10001010 "
b10001010 '
b10001100 $
b10001100 &
#282
b10001100 #
b10001100 (
b10001110 !
b10001110 %
b10001011 "
b10001011 '
b10001101 $
b10001101 &
#284
b10001101 #
b10001101 (
b10001111 !
b10001111 %
b10001100 "
b10001100 '
b10001110 $
b10001110 &
#286
b10001110 #
b10001110 (
b10010000 !
b10010000 %
b10001101 "
b10001101 '
b10001111 $
b10001111 &
#288
b10001111 #
b10001111 (
b10010001 !
b10010001 %
b10001110 "
b10001110 '
b10010000 $
b10010000 &
#290
b10010000 #
b10010000 (
b10010010 !
b10010010 %
b10001111 "
b10001111 '
b10010001 $
b10010001 &
#292
b10010001 #
b10010001 (
b10010011 !
b10010011 %
b10010000 "
b10010000 '
b10010010 $
b10010010 &
#294
b10010010 #
b10010010 (
b10010100 !
b10010100 %
b10010001 "
b10010001 '
b10010011 $
b10010011 &
#296
b10010011 #
b10010011 (
b10010101 !
b10010101 %
b10010010 "
b10010010 '
b10010100 $
b10010100 &
#298
b10010100 #
b10010100 (
b10010110 !
b10010110 %
b10010011 "
b10010011 '
b10010101 $
b10010101 &
#300
b10010101 #
b10010101 (
b10010111 !
b10010111 %
b10010100 "
b10010100 '
b10010110 $
b10010110 &
#302
b10010110 #
b10010110 (
b10011000 !
b10011000 %
b10010101 "
b10010101 '
b10010111 $
b10010111 &
#304
b10010111 #
b10010111 (
b10011001 !
b10011001 %
b10010110 "
b10010110 '
b10011000 $
b10011000 &
#306
b10011000 #
b10011000 (
b10011010 !
b10011010 %
b10010111 "
b10010111 '
b10011001 $
b10011001 &
#308
b10011001 #
b10011001 (
b10011011 !
b10011011 %
b10011000 "
b10011000 '
b10011010 $
b10011010 &
#310
b10011010 #
b10011010 (
b10011100 !
b10011100 %
b10011001 "
b10011001 '
b10011011 $
b10011011 &
#312
b10011011 #
b10011011 (
b10011101 !
b10011101 %
b10011010 "
b10011010 '
b10011100 $
b10011100 &
#314
b10011100 #
b10011100 (
b10011110 !
b10011110 %
b10011011 "
b10011011 '
b10011101 $
b10011101 &
#316
b10011101 #
b10011101 (
b10011111 !
b10011111 %
b10011100 "
b10011100 '
b10011110 $
b10011110 &
#318
b10011110 #
b10011110 (
b10100000 !
b10100000 %
b10011101 "
b10011101 '
b10011111 $
b10011111 &
#320
b10011111 #
b10011111 (
b10100001 !
b10100001 %
b10011110 "
b10011110 '
b10100000 $
b10100000 &
#322
b10100000 #
b10100000 (
b10100010 !
b10100010 %
b10011111 "
b10011111 '
b10100001 $
b10100001 &
#324
b10100001 #
b10100001 (
b10100011 !
b10100011 %
b10100000 "
b10100000 '
b10100010 $
b10100010 &
#326
b10100010 #
b10100010 (
b10100100 !
b10100100 %
b10100001 "
b10100001 '
b10100011 $
b10100011 &
#328
b10100011 #
b10100011 (
b10100101 !
b10100101 %
b10100010 "
b10100010 '
b10100100 $
b10100100 &
#330
b10100100 #
b10100100 (
b10100110 !
b10100110 %
b10100011 "
b10100011 '
b10100101 $
b10100101 &
#332
b10100101 #
b10100101 (
b10100111 !
b10100111 %
b10100100 "
b10100100 '
b10100110 $
b10100110 &
#334
b10100110 #
b10100110 (
b10101000 !
b10101000 %
b10100101 "
b10100101 '
b10100111 $
b10100111 &
#336
b10100111 #
b10100111 (
b10101001 !
b10101001 %
b10100110 "
b10100110 '
b10101000 $
b10101000 &
#338
b10101000 #
b10101000 (
b10101010 !
b10101010 %
b10100111 "
b10100111 '
b10101001 $
b10101001 &
#340
b10101001 #
b10101001 (
b10101011 !
b10101011 %
b10101000 "
b10101000 '
b10101010 $
b10101010 &
#342
b10101010 #
b10101010 (
b10101100 !
b10101100 %
b10101001 "
b10101001 '
b10101011 $
b10101011 &
#344
b10101011 #
b10101011 (
b10101101 !
b10101101 %
b10101010 "
b10101010 '
b10101100 $
b10101100 &
#346
b10101100 #
b10101100 (
b10101110 !
b10101110 %
b10101011 "
b10101011 '
b10101101 $
b10101101 &
#348
b10101101 #
b10101101 (
b10101111 !
b10101111 %
b10101100 "
b10101100 '
b10101110 $
b10101110 &
#350
b10101110 #
b10101110 (
b10110000 !
b10110000 %
b10101101 "
b10101101 '
b10101111 $
b10101111 &
#352
b10101111 #
b10101111 (
b10110001 !
b10110001 %
b10101110 "
b10101110 '
b10110000 $
b10110000 &
#354
b10110000 #
b10110000 (
b10110010 !
b10110010 %
b10101111 "
b10101111 '
b10110001 $
b10110001 &
#356
b10110001 #
b10110001 (
b10110011 !
b10110011 %
b10110000 "
b10110000 '
b10110010 $
b10110010 &
#358
b10110010 #
b10110010 (
b10110100 !
b10110100 %
b10110001 "
b10110001 '
b10110011 $
b10110011 &
#360
b10110011 #
b10110011 (
b10110101 !
b10110101 %
b10110010 "
b10110010 '
b10110100 $
b10110100 &
#362
b10110100 #
b10110100 (
b10110110 !
b10110110 %
b10110011 "
b10110011 '
b10110101 $
b10110101 &
#364
b10110101 #
b10110101 (
b10110111 !
b10110111 %
b10110100 "
b10110100 '
b10110110 $
b10110110 &
#366
b10110110 #
b10110110 (
b10111000 !
b10111000 %
b10110101 "
b10110101 '
b10110111 $
b10110111 &
#368
b10110111 #
b10110111 (
b10111001 !
b10111001 %
b10110110 "
b10110110 '
b10111000 $
b10111000 &
#370
b10111000 #
b10111000 (
b10111010 !
b10111010 %
b10110111 "
b10110111 '
b10111001 $
b10111001 &
#372
b10111001 #
b10111001 (
b10111011 !
b10111011 %
b10111000 "
b10111000 '
b10111010 $
b10111010 &
#374
b10111010 #
b10111010 (
b10111100 !
b10111100 %
b10111001 "
b10111001 '
b10111011 $
b10111011 &
#376
b10111011 #
b10111011 (
b10111101 !
b10111101 %
b10111010 "
b10111010 '
b10111100 $
b10111100 &
#378
b10111100 #
b10111100 (
b10111110 !
b10111110 %
b10111011 "
b10111011 '
b10111101 $
b10111101 &
#380
b10111101 #
b10111101 (
b10111111 !
b10111111 %
b10111100 "
b10111100 '
b10111110 $
b10111110 &
#382
b10111110 #
b10111110 (
b11000000 !
b11000000 %
b10111101 "
b10111101 '
b10111111 $
b10111111 &
#384
b10111111 #
b10111111 (
b11000001 !
b11000001 %
b10111110 "
b10111110 '
b11000000 $
b11000000 &
#386
b11000000 #
b11000000 (
b11000010 !
b11000010 %
b10111111 "
b10111111 '
b11000001 $
b11000001 &
#388
b11000001 #
b11000001 (
b11000011 !
b11000011 %
b11000000 "
b11000000 '
b11000010 $
b11000010 &
#390
b11000010 #
b11000010 (
b11000100 !
b11000100 %
b11000001 "
b11000001 '
b11000011 $
b11000011 &
#392
b11000011 #
b11000011 (
b11000101 !
b11000101 %
b11000010 "
b11000010 '
b11000100 $
b11000100 &
#394
b11000100 #
b11000100 (
b11000110 !
b11000110 %
b11000011 "
b11000011 '
b11000101 $
b11000101 &
#396
b11000101 #
b11000101 (
b11000111 !
b11000111 %
b11000100 "
b11000100 '
b11000110 $
b11000110 &
#398
b11000110 #
b11000110 (
b11001000 !
b11001000 %
b11000101 "
b11000101 '
b11000111 $
b11000111 &
#400
b11000111 #
b11000111 (
b11001001 !
b11001001 %
b11000110 "
b11000110 '
b11001000 $
b11001000 &
#402
b11001000 #
b11001000 (
b11001010 !
b11001010 %
b11000111 "
b11000111 '
b11001001 $
b11001001 &
#404
b11001001 #
b11001001 (
b11001011 !
b11001011 %
b11001000 "
b11001000 '
b11001010 $
b11001010 &
#406
b11001010 #
b11001010 (
b11001100 !
b11001100 %
b11001001 "
b11001001 '
b11001011 $
b11001011 &
#408
b11001011 #
b11001011 (
b11001101 !
b11001101 %
b11001010 "
b11001010 '
b11001100 $
b11001100 &
#410
b11001100 #
b11001100 (
b11001110 !
b11001110 %
b11001011 "
b11001011 '
b11001101 $
b11001101 &
#412
b11001101 #
b11001101 (
b11001111 !
b11001111 %
b11001100 "
b11001100 '
b11001110 $
b11001110 &
#414
b11001110 #
b11001110 (
b11010000 !
b11010000 %
b11001101 "
b11001101 '
b11001111 $
b11001111 &
#416
b11001111 #
b11001111 (
b11010001 !
b11010001 %
b11001110 "
b11001110 '
b11010000 $
b11010000 &
#418
b11010000 #
b11010000 (
b11010010 !
b11010010 %
b11001111 "
b11001111 '
b11010001 $
b11010001 &
#420
b11010001 #
b11010001 (
b11010011 !
b11010011 %
b11010000 "
b11010000 '
b11010010 $
b11010010 &
#422
b11010010 #
b11010010 (
b11010100 !
b11010100 %
b11010001 "
b11010001 '
b11010011 $
b11010011 &
#424
b11010011 #
b11010011 (
b11010101 !
b11010101 %
b11010010 "
b11010010 '
b11010100 $
b11010100 &
#426
b11010100 #
b11010100 (
b11010110 !
b11010110 %
b11010011 "
b11010011 '
b11010101 $
b11010101 &
#428
b11010101 #
b11010101 (
b11010111 !
b11010111 %
b11010100 "
b11010100 '
b11010110 $
b11010110 &
#430
b11010110 #
b11010110 (
b11011000 !
b11011000 %
b11010101 "
b11010101 '
b11010111 $
b11010111 &
#432
b11010111 #
b11010111 (
b11011001 !
b11011001 %
b11010110 "
b11010110 '
b11011000 $
b11011000 &
#434
b11011000 #
b11011000 (
b11011010 !
b11011010 %
b11010111 "
b11010111 '
b11011001 $
b11011001 &
#436
b11011001 #
b11011001 (
b11011011 !
b11011011 %
b11011000 "
b11011000 '
b11011010 $
b11011010 &
#438
b11011010 #
b11011010 (
b11011100 !
b11011100 %
b11011001 "
b11011001 '
b11011011 $
b11011011 &
#440
b11011011 #
b11011011 (
b11011101 !
b11011101 %
b11011010 "
b11011010 '
b11011100 $
b11011100 &
#442
b11011100 #
b11011100 (
b11011110 !
b11011110 %
b11011011 "
b11011011 '
b11011101 $
b11011101 &
#444
b11011101 #
b11011101 (
b11011111 !
b11011111 %
b11011100 "
b11011100 '
b11011110 $
b11011110 &
#446
b11011110 #
b11011110 (
b11100000 !
b11100000 %
b11011101 "
b11011101 '
b11011111 $
b11011111 &
#448
b11011111 #
b11011111 (
b11100001 !
b11100001 %
b11011110 "
b11011110 '
b11100000 $
b11100000 &
#450
b11100000 #
b11100000 (
b11100010 !
b11100010 %
b11011111 "
b11011111 '
b11100001 $
b11100001 &
#452
b11100001 #
b11100001 (
b11100011 !
b11100011 %
b11100000 "
b11100000 '
b11100010 $
b11100010 &
#454
b11100010 #
b11100010 (
b11100100 !
b11100100 %
b11100001 "
b11100001 '
b11100011 $
b11100011 &
#456
b11100011 #
b11100011 (
b11100101 !
b11100101 %
b11100010 "
b11100010 '
b11100100 $
b11100100 &
#458
b11100100 #
b11100100 (
b11100110 !
b11100110 %
b11100011 "
b11100011 '
b11100101 $
b11100101 &
#460
b11100101 #
b11100101 (
b11100111 !
b11100111 %
b11100100 "
b11100100 '
b11100110 $
b11100110 &
#462
b11100110 #
b11100110 (
b11101000 !
b11101000 %
b11100101 "
b11100101 '
b11100111 $
b11100111 &
#464
b11100111 #
b11100111 (
b11101001 !
b11101001 %
b11100110 "
b11100110 '
b11101000 $
b11101000 &
#466
b11101000 #
b11101000 (
b11101010 !
b11101010 %
b11100111 "
b11100111 '
b11101001 $
b11101001 &
#468
b11101001 #
b11101001 (
b11101011 !
b11101011 %
b11101000 "
b11101000 '
b11101010 $
b11101010 &
#470
b11101010 #
b11101010 (
b11101100 !
b11101100 %
b11101001 "
b11101001 '
b11101011 $
b11101011 &
#472
b11101011 #
b11101011 (
b11101101 !
b11101101 %
b11101010 "
b11101010 '
b11101100 $
b11101100 &
#474
b11101100 #
b11101100 (
b11101110 !
b11101110 %
b11101011 "
b11101011 '
b11101101 $
b11101101 &
#476
b11101101 #
b11101101 (
b11101111 !
b11101111 %
b11101100 "
b11101100 '
b11101110 $
b11101110 &
#478
b11101110 #
b11101110 (
b11110000 !
b11110000 %
b11101101 "
b11101101 '
b11101111 $
b11101111 &
#480
b11101111 #
b11101111 (
b11110001 !
b11110001 %
b11101110 "
b11101110 '
b11110000 $
b11110000 &
#482
b11110000 #
b11110000 (
b11110010 !
b11110010 %
b11101111 "
b11101111 '
b11110001 $
b11110001 &
#484
b11110001 #
b11110001 (
b11110011 !
b11110011 %
b11110000 "
b11110000 '
b11110010 $
b11110010 &
#486
b11110010 #
b11110010 (
b11110100 !
b11110100 %
b11110001 "
b11110001 '
b11110011 $
b11110011 &
#488
b11110011 #
b11110011 (
b11110101 !
b11110101 %
b11110010 "
b11110010 '
b11110100 $
b11110100 &
#490
b11110100 #
b11110100 (
b11110110 !
b11110110 %
b11110011 "
b11110011 '
b11110101 $
b11110101 &
#492
b11110101 #
b11110101 (
b11110111 !
b11110111 %
b11110100 "
b11110100 '
b11110110 $
b11110110 &
#494
b11110110 #
b11110110 (
b11111000 !
b11111000 %
b11110101 "
b11110101 '
b11110111 $
b11110111 &
#496
b11110111 #
b11110111 (
b11111001 !
b11111001 %
b11110110 "
b11110110 '
b11111000 $
b11111000 &
#498
b11111000 #
b11111000 (
b11111010 !
b11111010 %
b11110111 "
b11110111 '
b11111001 $
b11111001 &
#500
b11111001 #
b11111001 (
b11111011 !
b11111011 %
b11111000 "
b11111000 '
b11111010 $
b11111010 &
#502
b11111010 #
b11111010 (
b11111100 !
b11111100 %
b11111001 "
b11111001 '
b11111011 $
b11111011 &
#504
b11111011 #
b11111011 (
b11111101 !
b11111101 %
b11111010 "
b11111010 '
b11111100 $
b11111100 &
#506
b11111100 #
b11111100 (
b11111110 !
b11111110 %
b11111011 "
b11111011 '
b11111101 $
b11111101 &
