midterm/e5/mul8.v

module mul8(
    input clk,
    input logic[7:0] a,
    input logic[7:0] b,
    output logic[15:0] r
);
    logic[15:0] r_temp;
    always @(*) begin
        r_temp = a*b;
    end

    always_ff  @(posedge clk) begin
        r <= r_temp;
    end
endmodule

midterm/e5/mul16.v

module mul16(
    input clk,
    input logic[15:0] a,
    input logic[15:0] b,
    output logic[31:0] r
);
    // logic [7:0] aLow, aHigh, bLow, bHigh;
    logic [15:0] aLow_bLow, aHigh_bLow, aLow_bHigh, aHigh_bHigh;
    logic [16:0] aHbL_add;
    logic [31:0] temp_r, temp1, temp2;
    
    assign aHbL_add=aHigh_bLow + aLow_bHigh;

    always @(*) begin
        // aLow = (a & 16'h00FF); 
        // aHigh = (b & 16'hFF00) >> 8; 
        // bLow = (a & 16'h00FF); 
        // bHigh = (b & 16'hFF00) >> 8; 
        // temp1 = ;
        // temp2 = mHigh_nHigh << 16;
        temp_r = { 16'h0000, aLow_bLow } + {7'b0000000,aHbL_add,8'h00} + {aHigh_bHigh,16'h0000};
        //$display("a = %d", a);
        //$display("b = %d" , b);
        //$display("albl = %d", aLow_bLow);
        //$display("ahbl = %d", aHigh_bLow);
        //$display("albh = %d", aLow_bHigh);
        //$display("ahbh = %d", aHigh_bHigh);
    end

    mul8 mul1(.clk(clk), .a(a[7:0]), .b(b[7:0]), .r(aLow_bLow));
    mul8 mul2(.clk(clk), .a(a[15:8]), .b(b[7:0]), .r(aHigh_bLow));
    mul8 mul3(.clk(clk), .a(a[7:0]), .b(b[15:8]), .r(aLow_bHigh));
    mul8 mul4(.clk(clk), .a(a[15:8]), .b(b[15:8]), .r(aHigh_bHigh));

    always_ff  @(posedge clk) begin
        r <= temp_r;
    end


endmodule

midterm/e5/mul16_tb.v
module mul16_tb();
    logic clk;
    logic[15:0] a, a1, a2;
    logic[15:0] b, b1, b2;
    logic[31:0] r;

    initial begin
        $dumpfile("mul16.vcd");
        $dumpvars(0, mul16_tb);

        clk = 0;
        repeat(1000) begin
            #1;
            clk = ~clk;
        end
    end


    initial begin
        a = 60000;
        b = 50000;
        @(posedge clk);
        @(posedge clk);
        repeat (10) begin
            @(negedge clk)begin
                a = $urandom_range(0, 1024);
                b = $urandom_range(0, 1024);
            end
            @(posedge clk)
            #1;
            assert(r == (a2*b2)) else  $fatal(2, "a2 = %d, b2 = %d, r = %d", a2, b2, r);
            $display("a2 = %d, b2 = %d, r = %d", a2, b2, r);
        end

    end

    always_ff @(posedge clk) begin
        a1 <= a;
        a2 <= a1;
        b1 <= b;
        b2 <= b1;

    end

    mul16 m(
        .clk(clk),
        .a(a),
        .b(b),
        .r(r)
    );

endmodule

midterm/e5/mul16.vcd
$date
	Fri Nov 12 17:12:06 2021
$end
$version
	Icarus Verilog
$end
$timescale
	1s
$end
$scope module mul16_tb $end
$var wire 32 ! r [31:0] $end
$var reg 16 " a [15:0] $end
$var reg 16 # a1 [15:0] $end
$var reg 16 $ a2 [15:0] $end
$var reg 16 % b [15:0] $end
$var reg 16 & b1 [15:0] $end
$var reg 16 ' b2 [15:0] $end
$var reg 1 ( clk $end
$scope module m $end
$var wire 16 ) a [15:0] $end
$var wire 16 * b [15:0] $end
$var wire 1 ( clk $end
$var wire 16 + aLow_bLow [15:0] $end
$var wire 16 , aLow_bHigh [15:0] $end
$var wire 16 - aHigh_bLow [15:0] $end
$var wire 16 . aHigh_bHigh [15:0] $end
$var wire 17 / aHbL_add [16:0] $end
$var reg 32 0 r [31:0] $end
$var reg 32 1 temp_r [31:0] $end
$scope module mul1 $end
$var wire 8 2 a [7:0] $end
$var wire 8 3 b [7:0] $end
$var wire 1 ( clk $end
$var reg 16 4 r [15:0] $end
$var reg 16 5 r_temp [15:0] $end
$upscope $end
$scope module mul2 $end
$var wire 8 6 a [7:0] $end
$var wire 8 7 b [7:0] $end
$var wire 1 ( clk $end
$var reg 16 8 r [15:0] $end
$var reg 16 9 r_temp [15:0] $end
$upscope $end
$scope module mul3 $end
$var wire 8 : a [7:0] $end
$var wire 8 ; b [7:0] $end
$var wire 1 ( clk $end
$var reg 16 < r [15:0] $end
$var reg 16 = r_temp [15:0] $end
$upscope $end
$scope module mul4 $end
$var wire 8 > a [7:0] $end
$var wire 8 ? b [7:0] $end
$var wire 1 ( clk $end
$var reg 16 @ r [15:0] $end
$var reg 16 A r_temp [15:0] $end
$upscope $end
$upscope $end
$upscope $end
$enddefinitions $end
#0
$dumpvars
b1011001000111110 A
bx @
b11000011 ?
b11101010 >
b100100100100000 =
bx <
b11000011 ;
b1100000 :
b100100100100000 9
bx 8
b1010000 7
b11101010 6
b1111000000000 5
bx 4
b1010000 3
b1100000 2
bx 1
bx 0
bx /
bx .
bx -
bx ,
bx +
b1100001101010000 *
b1110101001100000 )
0(
bx '
bx &
b1100001101010000 %
bx $
bx #
b1110101001100000 "
bx !
$end
#1
b10110010110100000101111000000000 1
b1111000000000 +
b1111000000000 4
b1001001001000000 /
b100100100100000 -
b100100100100000 8
b100100100100000 ,
b100100100100000 <
b1011001000111110 .
b1011001000111110 @
b1100001101010000 &
b1110101001100000 #
1(
#2
0(
#3
b1100001101010000 '
b1110101001100000 $
b10110010110100000101111000000000 !
b10110010110100000101111000000000 0
1(
#4
b10010000 5
b100 9
b1001000 =
b10 A
b10 3
b10 7
b1 ;
b1 ?
b1001000 2
b10 6
b1001000 :
b10 >
b100000010 %
b100000010 *
b1001001000 "
b1001001000 )
0(
#5
b100100110010010000 1
b10010000 +
b10010000 4
b100 -
b100 8
b1001100 /
b1001000 ,
b1001000 <
b10 .
b10 @
b100000010 &
b1001001000 #
1(
#6
0(
#7
b100000010 '
b1001001000 $
b100100110010010000 !
b100100110010010000 0
1(
#8
b110111111110 5
b0 9
b0 =
b0 A
b11000111 3
b11000111 7
b0 ;
b0 ?
b10010 2
b0 6
b10010 :
b0 >
b11000111 %
b11000111 *
b10010 "
b10010 )
0(
#9
b110111111110 1
b110111111110 +
b110111111110 4
b0 -
b0 8
b0 /
b0 ,
b0 <
b0 .
b0 @
b11000111 &
b10010 #
1(
#10
0(
#11
b11000111 '
b10010 $
b110111111110 !
b110111111110 0
1(
#12
b1011110100 5
b111000 9
b1010001 =
b110 A
b11100 3
b11100 7
b11 ;
b11 ?
b11011 2
b10 6
b11011 :
b10 >
b1100011100 %
b1100011100 *
b1000011011 "
b1000011011 )
0(
#13
b1101000101111110100 1
b1011110100 +
b1011110100 4
b111000 -
b111000 8
b10001001 /
b1010001 ,
b1010001 <
b110 .
b110 @
b1100011100 &
b1000011011 #
1(
#14
0(
#15
b1100011100 '
b1000011011 $
b1101000101111110100 !
b1101000101111110100 0
1(
#16
b1110010001100 5
b0 9
b0 =
b0 A
b100100 3
b100100 7
b0 ;
b0 ?
b11001011 2
b0 6
b11001011 :
b0 >
b100100 %
b100100 *
b11001011 "
b11001011 )
0(
#17
b1110010001100 1
b1110010001100 +
b1110010001100 4
b0 -
b0 8
b0 /
b0 ,
b0 <
b0 .
b0 @
b100100 &
b11001011 #
1(
#18
0(
#19
b100100 '
b11001011 $
b1110010001100 !
b1110010001100 0
1(
#20
b1101100 5
b110110 9
b1000 =
b100 A
b11011 3
b11011 7
b10 ;
b10 ?
b100 2
b10 6
b100 :
b10 >
b1000011011 %
b1000011011 *
b1000000100 "
b1000000100 )
0(
#21
b1000011111001101100 1
b1101100 +
b1101100 4
b110110 -
b110110 8
b111110 /
b1000 ,
b1000 <
b100 .
b100 @
b1000011011 &
b1000000100 #
1(
#22
0(
#23
b1000011011 '
b1000000100 $
b1000011111001101100 !
b1000011111001101100 0
1(
#24
b11110100 9
b111000011110010 5
b111011010 =
b1111010 3
b1111010 7
b11101101 2
b11101101 :
b1001111010 %
b1001111010 *
b1011101101 "
b1011101101 )
0(
#25
b1110011111011110010 1
b111000011110010 +
b111000011110010 4
b11110100 -
b11110100 8
b1011001110 /
b111011010 ,
b111011010 <
b1001111010 &
b1011101101 #
1(
#26
0(
#27
b1001111010 '
b1011101101 $
b1110011111011110010 !
b1110011111011110010 0
1(
#28
b1010101111100 5
b1001011 9
b1010010100 =
b1001 A
b11001 3
b11001 7
b11 ;
b11 ?
b11011100 2
b11 6
b11011100 :
b11 >
b1100011001 %
b1100011001 *
b1111011100 "
b1111011100 )
0(
#29
b10111111010001111100 1
b1010101111100 +
b1010101111100 4
b1001011 -
b1001011 8
b1011011111 /
b1010010100 ,
b1010010100 <
b1001 .
b1001 @
b1100011001 &
b1111011100 #
1(
#30
0(
#31
b1100011001 '
b1111011100 $
b10111111010001111100 !
b10111111010001111100 0
1(
#32
b110100111 9
b11 A
b1000011001100100 5
b11110100 =
b10001101 3
b10001101 7
b1 ;
b1 ?
b11110100 2
b11110100 :
b110001101 %
b110001101 *
b1111110100 "
b1111110100 )
0(
#33
b1100010000101100100 1
b1000011001100100 +
b1000011001100100 4
b110100111 -
b110100111 8
b1010011011 /
b11110100 ,
b11110100 <
b11 .
b11 @
b110001101 &
b1111110100 #
1(
#34
0(
#35
b110001101 '
b1111110100 $
b1100010000101100100 !
b1100010000101100100 0
1(
#36
b10110111110000 5
b1010100 9
b10001100 =
b1 A
b1010100 3
b1010100 7
b10001100 2
b1 6
b10001100 :
b1 >
b101010100 %
b101010100 *
b110001100 "
b110001100 )
0(
#37
b100000110111110000 1
b10110111110000 +
b10110111110000 4
b1010100 -
b1010100 8
b11100000 /
b10001100 ,
b10001100 <
b1 .
b1 @
b101010100 &
b110001100 #
1(
#38
0(
#39
b101010100 '
b110001100 $
b100000110111110000 !
b100000110111110000 0
1(
#40
b1011110110000101 5
b1011001101 9
b0 =
b0 A
b11101111 3
b11101111 7
b0 ;
b0 ?
b11001011 2
b11 6
b11001011 :
b11 >
b11101111 %
b11101111 *
b1111001011 "
b1111001011 )
0(
#41
b111000101010000101 1
b1011110110000101 +
b1011110110000101 4
b1011001101 -
b1011001101 8
b1011001101 /
b0 ,
b0 <
b0 .
b0 @
b11101111 &
b1111001011 #
1(
#42
0(
#43
b11101111 '
b1111001011 $
b111000101010000101 !
b111000101010000101 0
1(
