midterm/e9_fsm/traffic.v
module traffic(
    input logic clk,
    input logic reset,
    output logic red,
    output logic orange,
    output logic green
);
    logic reset_1,count_red, count_green;

    always_ff @(posedge clk) begin
        reset_1 <= reset;
        if (reset_1 == 1 && reset == 0) begin
            red <= 1;
            orange <= 0;
            green <= 0;
            count_red <= 1;
            count_green <= 0;
        end
        else if (reset==0 && count_red==1 && red==1 && orange==0 && green==0) begin
            red <= 1;
            orange <= 0;
            green <= 0;
            count_red <= 0;
            count_green <= 0;
        end
        else if (reset==0 && count_red ==0 && red==1 && orange==0 && green==0)begin
            red <= 1;
            orange <= 1;
            green <= 0;
            count_red <= 0;
            count_green <= 0;
        end
        else if (reset==0 && red==1 && orange==1 && green==0)begin
            red <= 0;
            orange <= 0;
            green <= 1;
            count_red <= 0;
            count_green <= 1;
        end
        else if (reset==0 && count_green==1 && red==0 && orange==0 && green==1)begin
            red <= 0;
            orange <= 0;
            green <= 1;
            count_red <= 0;
            count_green <= 0;
        end
        else if (reset==0 && count_green==0 && red==0 && orange==0 && green==1)begin
            red <= 0;
            orange <= 1;
            green <= 0;
            count_red <= 0;
            count_green <= 0;
        end
    end
endmodule

midterm/e9_fsm/e9_fsm_tb.v
module e9_fsm_tb();
    logic clk,reset;
    logic orange,red,green;
    initial begin
        $dumpfile("e9_fsm_tb.vcd");
        $dumpvars(0, e9_fsm_tb);

        clk=0;
        reset=0;
        #5;
        clk=1;
        #5

        clk=0;
        reset=1;
        #5;
        clk=1;
        #5

        clk=0;
        reset=0;
        #5;
        clk=1;
        #5

        clk=0;
        repeat(100)begin
            #5;
            clk = !clk;
        end
    end

    traffic t1(
        .clk(clk),
        .reset(reset),
        .orange(orange),
        .red(red),
        .green(green)
    );
    
endmodule

midterm/e9_fsm/e9_fsm_tb.vcd
$date
	Fri Nov 12 15:42:15 2021
$end
$version
	Icarus Verilog
$end
$timescale
	1s
$end
$scope module e9_fsm_tb $end
$var wire 1 ! red $end
$var wire 1 " orange $end
$var wire 1 # green $end
$var reg 1 $ clk $end
$var reg 1 % reset $end
$scope module t1 $end
$var wire 1 $ clk $end
$var wire 1 % reset $end
$var reg 1 & count_green $end
$var reg 1 ' count_red $end
$var reg 1 # green $end
$var reg 1 " orange $end
$var reg 1 ! red $end
$var reg 1 ( reset_1 $end
$upscope $end
$upscope $end
$enddefinitions $end
#0
$dumpvars
x(
x'
x&
0%
0$
x#
x"
x!
$end
#5
0(
1$
#10
1%
0$
#15
1(
1$
#20
0%
0$
#25
0&
1'
0#
0"
1!
0(
1$
#30
0$
#35
0'
1$
#40
0$
#45
1"
1$
#50
0$
#55
1&
1#
0"
0!
1$
#60
0$
#65
0&
1$
#70
0$
#75
0#
1"
1$
