midterm/e1/raster.v

module raster(
    input logic clk,
    input logic reset,
    output logic[3:0] x,
    output logic[3:0] y
);

    logic[3:0] x_next,y_next;
    

    // do i need to build a clock here

    always_comb begin
        if (reset == 1) begin
            x = 0;
            y = 0;
            x_next = 0;
            y_next = 0;
            
        end
        else begin
            if (x < 11) begin
                x_next = x + 1;
                y_next = y;
            end
            else if (y <11) begin 
                x_next = 0;
                y_next = y+1;
            end
        
        end
    end

    always_ff @(posedge clk) begin
        x <= x_next;
        y <= y_next;
        
    end
 

endmodule

   // always @(posedge clk) begin
    //     if (reset == 1) begin
    //         #2; // how do we allow one cycle delay first
    //     end
    //     if (reset == 0) begin
    //             for (i = 0; i <= 11; i=i+1) begin
    //                 for (j = 0; j <= 11; j=j+1) begin
    //                     x = j;
    //                     y = i;  
    //                 end
    //             end
    //     end

    //     else begin // if always reset = 1 then reset to x=0, y=0
    //         x = 0;
    //         y = 0;
    //     end
    // end

midterm/e1/raster_tb.v
module raster_tb();
    logic clk;
    logic reset;
    logic[3:0] x, y;

    raster ras(
        .clk(clk),
        .reset(reset),
        .x(x),
        .y(y)
    );
    initial begin
        $dumpfile("raster_tb.vcd");
        $dumpvars(0,raster_tb);
        clk = 0;
        reset=1;
        #1

        clk=1;
        #1
        $display("reset= ",reset,"x= ",x," y= ", y);             

        clk=0;
        reset=0;
        #1
        
        clk=1;
        #1

        clk=0;

        repeat(143) begin
            $display("reset=",reset,", x=",x,", y=", y);            
            #1
            clk = 1;
            #1
            clk=0;
        end    
    end

    
endmodule
/*
- reset=1, x=?, y=?
- reset=0, x=?, y=?
- reset=0, x=0, y=0
- reset=0, x=1, y=0
- reset=0, x=2, y=0*/

midterm/e1/raster_tb.vcd
$date
	Fri Nov 12 16:48:54 2021
$end
$version
	Icarus Verilog
$end
$timescale
	1s
$end
$scope module raster_tb $end
$var wire 4 ! y [3:0] $end
$var wire 4 " x [3:0] $end
$var reg 1 # clk $end
$var reg 1 $ reset $end
$scope module ras $end
$var wire 1 # clk $end
$var wire 1 $ reset $end
$var reg 4 % x [3:0] $end
$var reg 4 & x_next [3:0] $end
$var reg 4 ' y [3:0] $end
$var reg 4 ( y_next [3:0] $end
$upscope $end
$upscope $end
$enddefinitions $end
#0
$dumpvars
b0 (
b0 '
b0 &
b0 %
1$
0#
b0 "
b0 !
$end
#1
1#
#2
b1 &
0$
0#
#3
b10 &
b1 "
b1 %
1#
#4
0#
#5
b11 &
b10 "
b10 %
1#
#6
0#
#7
b100 &
b11 "
b11 %
1#
#8
0#
#9
b101 &
b100 "
b100 %
1#
#10
0#
#11
b110 &
b101 "
b101 %
1#
#12
0#
#13
b111 &
b110 "
b110 %
1#
#14
0#
#15
b1000 &
b111 "
b111 %
1#
#16
0#
#17
b1001 &
b1000 "
b1000 %
1#
#18
0#
#19
b1010 &
b1001 "
b1001 %
1#
#20
0#
#21
b1011 &
b1010 "
b1010 %
1#
#22
0#
#23
b1 (
b0 &
b1011 "
b1011 %
1#
#24
0#
#25
b1 &
b1 !
b1 '
b0 "
b0 %
1#
#26
0#
#27
b10 &
b1 "
b1 %
1#
#28
0#
#29
b11 &
b10 "
b10 %
1#
#30
0#
#31
b100 &
b11 "
b11 %
1#
#32
0#
#33
b101 &
b100 "
b100 %
1#
#34
0#
#35
b110 &
b101 "
b101 %
1#
#36
0#
#37
b111 &
b110 "
b110 %
1#
#38
0#
#39
b1000 &
b111 "
b111 %
1#
#40
0#
#41
b1001 &
b1000 "
b1000 %
1#
#42
0#
#43
b1010 &
b1001 "
b1001 %
1#
#44
0#
#45
b1011 &
b1010 "
b1010 %
1#
#46
0#
#47
b10 (
b0 &
b1011 "
b1011 %
1#
#48
0#
#49
b1 &
b10 !
b10 '
b0 "
b0 %
1#
#50
0#
#51
b10 &
b1 "
b1 %
1#
#52
0#
#53
b11 &
b10 "
b10 %
1#
#54
0#
#55
b100 &
b11 "
b11 %
1#
#56
0#
#57
b101 &
b100 "
b100 %
1#
#58
0#
#59
b110 &
b101 "
b101 %
1#
#60
0#
#61
b111 &
b110 "
b110 %
1#
#62
0#
#63
b1000 &
b111 "
b111 %
1#
#64
0#
#65
b1001 &
b1000 "
b1000 %
1#
#66
0#
#67
b1010 &
b1001 "
b1001 %
1#
#68
0#
#69
b1011 &
b1010 "
b1010 %
1#
#70
0#
#71
b11 (
b0 &
b1011 "
b1011 %
1#
#72
0#
#73
b1 &
b11 !
b11 '
b0 "
b0 %
1#
#74
0#
#75
b10 &
b1 "
b1 %
1#
#76
0#
#77
b11 &
b10 "
b10 %
1#
#78
0#
#79
b100 &
b11 "
b11 %
1#
#80
0#
#81
b101 &
b100 "
b100 %
1#
#82
0#
#83
b110 &
b101 "
b101 %
1#
#84
0#
#85
b111 &
b110 "
b110 %
1#
#86
0#
#87
b1000 &
b111 "
b111 %
1#
#88
0#
#89
b1001 &
b1000 "
b1000 %
1#
#90
0#
#91
b1010 &
b1001 "
b1001 %
1#
#92
0#
#93
b1011 &
b1010 "
b1010 %
1#
#94
0#
#95
b100 (
b0 &
b1011 "
b1011 %
1#
#96
0#
#97
b1 &
b100 !
b100 '
b0 "
b0 %
1#
#98
0#
#99
b10 &
b1 "
b1 %
1#
#100
0#
#101
b11 &
b10 "
b10 %
1#
#102
0#
#103
b100 &
b11 "
b11 %
1#
#104
0#
#105
b101 &
b100 "
b100 %
1#
#106
0#
#107
b110 &
b101 "
b101 %
1#
#108
0#
#109
b111 &
b110 "
b110 %
1#
#110
0#
#111
b1000 &
b111 "
b111 %
1#
#112
0#
#113
b1001 &
b1000 "
b1000 %
1#
#114
0#
#115
b1010 &
b1001 "
b1001 %
1#
#116
0#
#117
b1011 &
b1010 "
b1010 %
1#
#118
0#
#119
b101 (
b0 &
b1011 "
b1011 %
1#
#120
0#
#121
b1 &
b101 !
b101 '
b0 "
b0 %
1#
#122
0#
#123
b10 &
b1 "
b1 %
1#
#124
0#
#125
b11 &
b10 "
b10 %
1#
#126
0#
#127
b100 &
b11 "
b11 %
1#
#128
0#
#129
b101 &
b100 "
b100 %
1#
#130
0#
#131
b110 &
b101 "
b101 %
1#
#132
0#
#133
b111 &
b110 "
b110 %
1#
#134
0#
#135
b1000 &
b111 "
b111 %
1#
#136
0#
#137
b1001 &
b1000 "
b1000 %
1#
#138
0#
#139
b1010 &
b1001 "
b1001 %
1#
#140
0#
#141
b1011 &
b1010 "
b1010 %
1#
#142
0#
#143
b110 (
b0 &
b1011 "
b1011 %
1#
#144
0#
#145
b1 &
b110 !
b110 '
b0 "
b0 %
1#
#146
0#
#147
b10 &
b1 "
b1 %
1#
#148
0#
#149
b11 &
b10 "
b10 %
1#
#150
0#
#151
b100 &
b11 "
b11 %
1#
#152
0#
#153
b101 &
b100 "
b100 %
1#
#154
0#
#155
b110 &
b101 "
b101 %
1#
#156
0#
#157
b111 &
b110 "
b110 %
1#
#158
0#
#159
b1000 &
b111 "
b111 %
1#
#160
0#
#161
b1001 &
b1000 "
b1000 %
1#
#162
0#
#163
b1010 &
b1001 "
b1001 %
1#
#164
0#
#165
b1011 &
b1010 "
b1010 %
1#
#166
0#
#167
b111 (
b0 &
b1011 "
b1011 %
1#
#168
0#
#169
b1 &
b111 !
b111 '
b0 "
b0 %
1#
#170
0#
#171
b10 &
b1 "
b1 %
1#
#172
0#
#173
b11 &
b10 "
b10 %
1#
#174
0#
#175
b100 &
b11 "
b11 %
1#
#176
0#
#177
b101 &
b100 "
b100 %
1#
#178
0#
#179
b110 &
b101 "
b101 %
1#
#180
0#
#181
b111 &
b110 "
b110 %
1#
#182
0#
#183
b1000 &
b111 "
b111 %
1#
#184
0#
#185
b1001 &
b1000 "
b1000 %
1#
#186
0#
#187
b1010 &
b1001 "
b1001 %
1#
#188
0#
#189
b1011 &
b1010 "
b1010 %
1#
#190
0#
#191
b1000 (
b0 &
b1011 "
b1011 %
1#
#192
0#
#193
b1 &
b1000 !
b1000 '
b0 "
b0 %
1#
#194
0#
#195
b10 &
b1 "
b1 %
1#
#196
0#
#197
b11 &
b10 "
b10 %
1#
#198
0#
#199
b100 &
b11 "
b11 %
1#
#200
0#
#201
b101 &
b100 "
b100 %
1#
#202
0#
#203
b110 &
b101 "
b101 %
1#
#204
0#
#205
b111 &
b110 "
b110 %
1#
#206
0#
#207
b1000 &
b111 "
b111 %
1#
#208
0#
#209
b1001 &
b1000 "
b1000 %
1#
#210
0#
#211
b1010 &
b1001 "
b1001 %
1#
#212
0#
#213
b1011 &
b1010 "
b1010 %
1#
#214
0#
#215
b1001 (
b0 &
b1011 "
b1011 %
1#
#216
0#
#217
b1 &
b1001 !
b1001 '
b0 "
b0 %
1#
#218
0#
#219
b10 &
b1 "
b1 %
1#
#220
0#
#221
b11 &
b10 "
b10 %
1#
#222
0#
#223
b100 &
b11 "
b11 %
1#
#224
0#
#225
b101 &
b100 "
b100 %
1#
#226
0#
#227
b110 &
b101 "
b101 %
1#
#228
0#
#229
b111 &
b110 "
b110 %
1#
#230
0#
#231
b1000 &
b111 "
b111 %
1#
#232
0#
#233
b1001 &
b1000 "
b1000 %
1#
#234
0#
#235
b1010 &
b1001 "
b1001 %
1#
#236
0#
#237
b1011 &
b1010 "
b1010 %
1#
#238
0#
#239
b1010 (
b0 &
b1011 "
b1011 %
1#
#240
0#
#241
b1 &
b1010 !
b1010 '
b0 "
b0 %
1#
#242
0#
#243
b10 &
b1 "
b1 %
1#
#244
0#
#245
b11 &
b10 "
b10 %
1#
#246
0#
#247
b100 &
b11 "
b11 %
1#
#248
0#
#249
b101 &
b100 "
b100 %
1#
#250
0#
#251
b110 &
b101 "
b101 %
1#
#252
0#
#253
b111 &
b110 "
b110 %
1#
#254
0#
#255
b1000 &
b111 "
b111 %
1#
#256
0#
#257
b1001 &
b1000 "
b1000 %
1#
#258
0#
#259
b1010 &
b1001 "
b1001 %
1#
#260
0#
#261
b1011 &
b1010 "
b1010 %
1#
#262
0#
#263
b1011 (
b0 &
b1011 "
b1011 %
1#
#264
0#
#265
b1 &
b1011 !
b1011 '
b0 "
b0 %
1#
#266
0#
#267
b10 &
b1 "
b1 %
1#
#268
0#
#269
b11 &
b10 "
b10 %
1#
#270
0#
#271
b100 &
b11 "
b11 %
1#
#272
0#
#273
b101 &
b100 "
b100 %
1#
#274
0#
#275
b110 &
b101 "
b101 %
1#
#276
0#
#277
b111 &
b110 "
b110 %
1#
#278
0#
#279
b1000 &
b111 "
b111 %
1#
#280
0#
#281
b1001 &
b1000 "
b1000 %
1#
#282
0#
#283
b1010 &
b1001 "
b1001 %
1#
#284
0#
#285
b1011 &
b1010 "
b1010 %
1#
#286
0#
#287
b1011 "
b1011 %
1#
